{"type": "Feature", "id": 12510442, "properties": {"woe:id": 12510442, "woe:parent_id": 1262220, "woe:name": "Malanje Airport", "woe:placetype": 14, "woe:placetype_name": "Airport", "woe:lang": "ENG", "iso:country": "AO", "meta:provider": ["geoplanet:7.3.1", "geoplanet:7.3.2", "geoplanet:7.4.0", "geoplanet:7.4.1", "geoplanet:7.5.1", "geoplanet:7.5.2", "geoplanet:7.6.0", "geoplanet:7.8.1", "geoplanet:7.9.0", "geoplanet:7.10.0", "geoplanet:8.0.0", "woeplanet:8.0.0"], "meta:indexed": "2020-08-20T21:02:12.400972", "woe:alias_ENG_V": ["MEG Airport", "MEG"], "meta:updated": "2020-08-22T03:00:17.653859", "woe:hierarchy": {"continent": 24865670, "country": 23424745, "town": 0, "planet": 1, "county": 0, "suburb": 0, "state": 2344666, "region": 0, "localadmin": 0}, "woe:timezone_id": 28350712, "woe:hash": "kq79g62c18q3", "woe:centroid": [16.3158, -9.5236], "geom:latitude": -9.5236, "geom:longitude": 16.3158, "geom:hash": "kq79g62c18q3", "woe:latitude": -9.5236, "geom:centroid": [16.3158, -9.5236], "woe:longitude": 16.3158, "woe:repo": "woeplanet-airport-ao"}, "geometry": {"coordinates": [16.3158, -9.5236], "type": "Point"}}