{"type": "Feature", "id": 12510446, "geometry": {"type": "Point", "coordinates": [12.1483, -15.2592]}, "properties": {"woe:id": 12510446, "woe:parent_id": 1262954, "woe:name": "Mocamedes New Airport", "woe:placetype": 14, "woe:placetype_name": "Airport", "woe:lang": "ENG", "iso:country": "AO", "meta:provider": ["geoplanet:7.3.1", "geoplanet:7.3.2", "geoplanet:7.4.0", "geoplanet:7.4.1", "geoplanet:7.5.1", "geoplanet:7.5.2", "geoplanet:7.6.0", "geoplanet:7.8.1", "geoplanet:7.9.0", "geoplanet:7.10.0", "geoplanet:8.0.0", "woeplanet:8.0.0"], "meta:indexed": "2020-08-20T21:02:12.404321", "meta:updated": "2020-10-14T11:08:41.753818", "woe:hierarchy": {"continent": 24865670, "country": 23424745, "town": 0, "planet": 1, "county": 0, "suburb": 0, "state": 2344667, "region": 0, "localadmin": 0}, "woe:timezone_id": 28350712, "woe:hash": "km29hqnheyvn", "woe:centroid": [12.1483, -15.2592], "geom:latitude": -15.2592, "geom:longitude": 12.1483, "geom:hash": "km29hqnheyvn", "woe:latitude": -15.2592, "geom:centroid": [12.1483, -15.2592], "woe:longitude": 12.1483, "woe:repo": "woeplanet-airport-ao", "geom:area": 0.0, "woe:scale": 19}}