{"type": "Feature", "id": 12510433, "geometry": {"type": "Point", "coordinates": [20.805, -7.3561]}, "properties": {"woe:id": 12510433, "woe:parent_id": 1261893, "woe:name": "Chitato Airport", "woe:placetype": 14, "woe:placetype_name": "Airport", "woe:lang": "ENG", "iso:country": "AO", "meta:provider": ["geoplanet:7.3.1", "geoplanet:7.3.2", "geoplanet:7.4.0", "geoplanet:7.4.1", "geoplanet:7.5.1", "geoplanet:7.5.2", "geoplanet:7.6.0", "geoplanet:7.8.1", "geoplanet:7.9.0", "geoplanet:7.10.0", "geoplanet:8.0.0", "woeplanet:8.0.0"], "meta:indexed": "2020-08-20T21:02:12.393672", "woe:alias_ENG_V": ["PGI Airport", "PGI"], "meta:updated": "2020-10-14T11:08:41.751723", "woe:hierarchy": {"continent": 24865670, "country": 23424745, "town": 0, "planet": 1, "county": 0, "suburb": 0, "state": 2344671, "region": 0, "localadmin": 0}, "woe:timezone_id": 28350712, "woe:hash": "kqwy1kvexes6", "woe:centroid": [20.805, -7.3561], "geom:latitude": -7.3561, "geom:longitude": 20.805, "geom:hash": "kqwy1kvexes6", "woe:latitude": -7.3561, "geom:centroid": [20.805, -7.3561], "woe:longitude": 20.805, "woe:repo": "woeplanet-airport-ao", "geom:area": 0.0, "woe:scale": 19}}